{
  "date": "2026-02-27",
  "summary": "### 🤖 AI & 大模型\n- 抖音上线长图文功能，由AI驱动内容创作，扶持深度内容。\n  原文: https://36kr.com/p/3700444303814536?f=rss\n- 具身智能公司“中科第五纪”获数亿元融资，为宇树机器人提供“大脑”。\n  原文: https://36kr.com/p/3700919151538052?f=rss\n- 机器人基础模型公司“智平方”完成超10亿元B轮融资，估值超百亿。\n  原文: http://www.cyzone.cn/article/825165.html\n- 具身智能企业“千寻智能”完成近20亿元融资，云锋基金、红杉等参投。\n  原文: http://www.cyzone.cn/article/825160.html\n- 豆包手机回应安全漏洞传闻，称已升级防护并谴责黑公关行为。\n  原文: https://36kr.com/newsflashes/3701042411663236?f=rss\n\n### 💻 科技前沿\n- 德国总理默茨参访宇树科技，关注中国机器人技术发展。\n  原文: https://36kr.com/p/3700794963193734?f=rss\n- AWE2026将设“创新科技展区”，聚焦家电与消费电子产业升级。\n  原文: https://36kr.com/p/3700996120915848?f=rss\n- 高精度金属3D打印公司“云耀深维”连融两轮，用于技术研发与产能提升。\n  原文: https://36kr.com/p/3700876701642374?f=rss\n- 字节跳动旗下懂车帝据悉正考虑在香港进行IPO。\n  原文: https://36kr.com/newsflashes/3701040036851585?f=rss\n- 魅族手机业务被曝实质性停摆，预计将于3月正式退市。\n  原文: https://36kr.com/p/3699924181134984?f=rss\n\n### 💰 创投动态\n- 携程集团总裁范敏、董事季琦双双辞职，公司任命新独立董事。\n  原文: http://\n- 静水湖创投新一期S基金超募设立并完成交割，专注接续投资。\n  原文: http://www.cyzone.cn/article/825197.html\n- 刘强东创立游艇品牌“Sea Expandary”，已与深圳、珠海政府签约。\n  原文: http://\n- 云南省国有资本运营公司增资至199亿元，增幅约12%。\n  原文: http://\n- 2026电影经济促进年启动，全年预计投放不低于300亿元消费信贷。\n  原文: http://",
  "news_items": [
    {
      "category": "AI",
      "title": "抖音上线长图文功能，由AI驱动内容创作，扶持深度内容。",
      "link": "",
      "source": ""
    },
    {
      "category": "AI",
      "title": "具身智能公司“中科第五纪”获数亿元融资，为宇树机器人提供“大脑”。",
      "link": "https://36kr.com/p/3700919151538052?f=rss",
      "source": "36Kr科技"
    },
    {
      "category": "AI",
      "title": "机器人基础模型公司“智平方”完成超10亿元B轮融资，估值超百亿。",
      "link": "http://www.cyzone.cn/article/824599.html",
      "source": "创业邦"
    },
    {
      "category": "AI",
      "title": "具身智能企业“千寻智能”完成近20亿元融资，云锋基金、红杉等参投。",
      "link": "http://www.cyzone.cn/article/825160.html",
      "source": "创业邦"
    },
    {
      "category": "AI",
      "title": "豆包手机回应安全漏洞传闻，称已升级防护并谴责黑公关行为。",
      "link": "https://36kr.com/newsflashes/3701042411663236?f=rss",
      "source": "36Kr科技"
    },
    {
      "category": "科技",
      "title": "高精度金属3D打印公司“云耀深维”连融两轮，用于技术研发与产能提升。",
      "link": "https://36kr.com/p/3700876701642374?f=rss",
      "source": "36Kr科技"
    },
    {
      "category": "科技",
      "title": "字节跳动旗下懂车帝据悉正考虑在香港进行IPO。",
      "link": "https://36kr.com/newsflashes/3701040036851585?f=rss",
      "source": "36Kr科技"
    },
    {
      "category": "科技",
      "title": "魅族手机业务被曝实质性停摆，预计将于3月正式退市。",
      "link": "https://36kr.com/p/3699924181134984?f=rss",
      "source": "36Kr科技"
    },
    {
      "category": "创投",
      "title": "携程集团总裁范敏、董事季琦双双辞职，公司任命新独立董事。",
      "link": "",
      "source": ""
    },
    {
      "category": "创投",
      "title": "刘强东创立游艇品牌“Sea Expandary”，已与深圳、珠海政府签约。",
      "link": "",
      "source": ""
    },
    {
      "category": "创投",
      "title": "云南省国有资本运营公司增资至199亿元，增幅约12%。",
      "link": "http://",
      "source": "创业邦"
    },
    {
      "category": "创投",
      "title": "2026电影经济促进年启动，全年预计投放不低于300亿元消费信贷。",
      "link": "http://",
      "source": "创业邦"
    }
  ],
  "total_articles": 60,
  "generated_at": "2026-02-27T12:26:06.512988+08:00"
}